geqo/__deps__.py
geqo/__init__.py
geqo/__logger__.py
geqo/plugin.py
geqo/algorithms/__init__.py
geqo/algorithms/algorithms.py
geqo/algorithms/risk_model.py
geqo/core/__init__.py
geqo/core/basic.py
geqo/core/quantum_circuit.py
geqo/core/quantum_operation.py
geqo/gates/__init__.py
geqo/gates/fundamental_gates.py
geqo/gates/multi_qubit_gates.py
geqo/gates/rotation_gates.py
geqo/initialization/__init__.py
geqo/initialization/state.py
geqo/operations/__init__.py
geqo/operations/controls.py
geqo/operations/measurement.py
geqo/simulators/__init__.py
geqo/simulators/base.py
geqo/simulators/cupy/__init__.py
geqo/simulators/cupy/implementation.py
geqo/simulators/numpy/__init__.py
geqo/simulators/numpy/implementation.py
geqo/simulators/sympy/__init__.py
geqo/simulators/sympy/implementation.py
geqo/utils/__init__.py
geqo/utils/_all_/helpers.py
geqo/utils/_base_/helpers.py
geqo/utils/_cupy_/helpers.py
geqo/utils/_numpy_/helpers.py
geqo/utils/_sympy_/helpers.py
geqo/visualization/__init__.py
geqo/visualization/common.py
geqo/visualization/latex.py
geqo/visualization/mpl.py
geqo-0.1.2.dist-info/METADATA
geqo-0.1.2.dist-info/WHEEL
geqo-0.1.2.dist-info/licenses/LICENSE
geqo-0.1.2.dist-info/RECORD
